setup.py
tiagotele_distributions/Binomialdistribution.py
tiagotele_distributions/Gaussiandistribution.py
tiagotele_distributions/Generaldistribution.py
tiagotele_distributions/__init__.py
tiagotele_distributions.egg-info/PKG-INFO
tiagotele_distributions.egg-info/SOURCES.txt
tiagotele_distributions.egg-info/dependency_links.txt
tiagotele_distributions.egg-info/not-zip-safe
tiagotele_distributions.egg-info/top_level.txt