Metadata-Version: 1.0
Name: tiagotele-distributions
Version: 0.1
Summary: Distributions made by Tiago Melo.
Home-page: UNKNOWN
Author: UNKNOWN
Author-email: UNKNOWN
License: UNKNOWN
Platform: UNKNOWN
